sybil/__init__.py
sybil/document.py
sybil/example.py
sybil/py.typed
sybil/python.py
sybil/region.py
sybil/sybil.py
sybil/text.py
sybil/typing.py
sybil/evaluators/__init__.py
sybil/evaluators/capture.py
sybil/evaluators/doctest.py
sybil/evaluators/python.py
sybil/evaluators/skip.py
sybil/integration/__init__.py
sybil/integration/pytest.py
sybil/integration/unittest.py
sybil/parsers/__init__.py
sybil/parsers/capture.py
sybil/parsers/codeblock.py
sybil/parsers/doctest.py
sybil/parsers/skip.py
sybil/parsers/abstract/__init__.py
sybil/parsers/abstract/clear.py
sybil/parsers/abstract/codeblock.py
sybil/parsers/abstract/doctest.py
sybil/parsers/abstract/lexers.py
sybil/parsers/abstract/skip.py
sybil/parsers/markdown/__init__.py
sybil/parsers/markdown/clear.py
sybil/parsers/markdown/codeblock.py
sybil/parsers/markdown/lexers.py
sybil/parsers/markdown/skip.py
sybil/parsers/myst/__init__.py
sybil/parsers/myst/clear.py
sybil/parsers/myst/codeblock.py
sybil/parsers/myst/doctest.py
sybil/parsers/myst/lexers.py
sybil/parsers/myst/skip.py
sybil/parsers/rest/__init__.py
sybil/parsers/rest/capture.py
sybil/parsers/rest/clear.py
sybil/parsers/rest/codeblock.py
sybil/parsers/rest/doctest.py
sybil/parsers/rest/lexers.py
sybil/parsers/rest/skip.py
sybil-9.2.0.dist-info/licenses/LICENSE.txt
sybil-9.2.0.dist-info/METADATA
sybil-9.2.0.dist-info/WHEEL
sybil-9.2.0.dist-info/top_level.txt
sybil-9.2.0.dist-info/RECORD
