Metadata-Version: 2.4
Name: sybil
Version: 9.2.0
Summary: Automated testing for the examples in your code and documentation.
Home-page: https://github.com/simplistix/sybil
Author: Chris Withers
Author-email: chris@withers.org
License: MIT
Classifier: Intended Audience :: Developers
Classifier: License :: OSI Approved :: MIT License
Classifier: Programming Language :: Python :: 3
Requires-Python: >=3.9
License-File: LICENSE.txt
Provides-Extra: pytest
Requires-Dist: pytest>=8; extra == "pytest"
Provides-Extra: test
Requires-Dist: mypy; extra == "test"
Requires-Dist: myst_parser; extra == "test"
Requires-Dist: pytest>=8; extra == "test"
Requires-Dist: pytest-cov; extra == "test"
Requires-Dist: seedir; extra == "test"
Requires-Dist: testfixtures; extra == "test"
Requires-Dist: types-PyYAML; extra == "test"
Provides-Extra: docs
Requires-Dist: furo; extra == "docs"
Requires-Dist: sphinx; extra == "docs"
Provides-Extra: release
Requires-Dist: twine; extra == "release"
Requires-Dist: wheel; extra == "release"
Dynamic: author
Dynamic: author-email
Dynamic: classifier
Dynamic: description
Dynamic: home-page
Dynamic: license
Dynamic: license-file
Dynamic: provides-extra
Dynamic: requires-python
Dynamic: summary
